{ "compressionlevel":-1,
 "height":18,
 "infinite":false,
 "layers":[
        {
         "id":6,
         "image":"..\/img\/room\/home\/room.png",
         "name":"room",
         "opacity":1,
         "type":"imagelayer",
         "visible":false,
         "x":0,
         "y":0
        }, 
        {
         "data":[0, 0, 0, 0, 0, 0, 0, 0, 0, 0, 0, 0, 0, 0, 0, 0, 0, 0, 0, 0, 0, 0, 0, 0, 0, 0, 0, 0,
            0, 0, 0, 0, 0, 0, 0, 0, 0, 0, 0, 0, 0, 0, 0, 0, 0, 0, 0, 0, 0, 0, 0, 0, 0, 0, 0, 0,
            0, 0, 0, 0, 0, 0, 0, 0, 0, 0, 0, 0, 0, 0, 0, 0, 0, 0, 0, 0, 0, 0, 0, 0, 0, 0, 0, 0,
            0, 0, 0, 0, 0, 0, 0, 0, 0, 0, 0, 0, 0, 0, 0, 9, 10, 10, 10, 10, 10, 10, 10, 10, 11, 0, 0, 0,
            0, 0, 0, 0, 0, 0, 0, 0, 0, 0, 0, 0, 0, 0, 0, 16, 17, 17, 17, 17, 17, 17, 17, 17, 18, 0, 0, 0,
            0, 0, 0, 0, 0, 0, 0, 0, 0, 0, 0, 0, 0, 0, 0, 16, 17, 17, 17, 17, 17, 17, 17, 17, 18, 0, 0, 0,
            0, 0, 0, 0, 0, 0, 0, 9, 10, 10, 10, 10, 10, 11, 0, 16, 17, 17, 17, 17, 17, 17, 17, 17, 18, 0, 0, 0,
            0, 0, 0, 0, 0, 0, 0, 16, 17, 17, 17, 17, 17, 18, 0, 16, 17, 17, 17, 17, 17, 17, 17, 17, 18, 0, 0, 0,
            0, 0, 0, 0, 0, 0, 0, 16, 17, 17, 17, 17, 17, 18, 0, 16, 17, 17, 17, 17, 17, 17, 17, 17, 18, 0, 0, 0,
            0, 0, 0, 0, 0, 0, 0, 16, 17, 17, 17, 17, 17, 18, 0, 23, 52, 24, 24, 24, 24, 24, 24, 24, 25, 0, 0, 0,
            0, 9, 10, 10, 10, 11, 0, 16, 17, 17, 17, 17, 17, 18, 0, 0, 14, 0, 0, 0, 0, 0, 0, 0, 0, 0, 0, 0,
            0, 16, 17, 17, 17, 18, 0, 16, 17, 17, 17, 17, 17, 35, 10, 10, 38, 10, 11, 0, 9, 10, 10, 10, 10, 10, 11, 0,
            0, 16, 17, 17, 17, 18, 0, 16, 17, 17, 17, 17, 17, 17, 17, 17, 17, 17, 18, 0, 16, 17, 17, 17, 17, 17, 18, 0,
            0, 16, 17, 17, 17, 46, 6, 44, 17, 17, 17, 17, 17, 17, 17, 17, 17, 17, 46, 6, 44, 17, 17, 17, 17, 17, 18, 0,
            0, 16, 17, 17, 17, 18, 0, 16, 17, 17, 17, 17, 17, 17, 17, 17, 17, 17, 18, 0, 16, 17, 17, 17, 17, 17, 18, 0,
            0, 16, 17, 17, 17, 18, 0, 16, 17, 17, 17, 17, 17, 17, 17, 17, 17, 17, 18, 0, 23, 24, 24, 24, 24, 24, 25, 0,
            0, 23, 24, 24, 24, 25, 0, 23, 24, 24, 24, 24, 24, 24, 24, 24, 24, 24, 25, 0, 0, 0, 0, 0, 0, 0, 0, 0,
            0, 0, 0, 0, 0, 0, 0, 0, 0, 0, 0, 0, 0, 0, 0, 0, 0, 0, 0, 0, 0, 0, 0, 0, 0, 0, 0, 0],
         "height":18,
         "id":9,
         "name":"floor",
         "opacity":1,
         "type":"tilelayer",
         "visible":true,
         "width":28,
         "x":0,
         "y":0
        }, 
        {
         "id":8,
         "image":"..\/img\/room\/home\/foreground.png",
         "name":"foregroundImg",
         "opacity":1,
         "type":"imagelayer",
         "visible":false,
         "x":0,
         "y":0
        }, 
        {
         "data":[0, 0, 0, 0, 0, 0, 0, 0, 0, 0, 0, 0, 0, 0, 0, 0, 0, 0, 0, 0, 0, 0, 0, 0, 0, 0, 0, 0,
            0, 0, 0, 0, 0, 0, 0, 0, 0, 0, 0, 0, 0, 0, 0, 69, 70, 70, 70, 70, 70, 70, 70, 70, 71, 0, 0, 0,
            0, 0, 0, 0, 0, 0, 0, 0, 0, 0, 0, 0, 0, 0, 0, 78, 79, 79, 79, 79, 79, 79, 79, 79, 80, 0, 0, 0,
            0, 0, 0, 0, 0, 0, 0, 0, 0, 0, 0, 0, 0, 0, 0, 0, 0, 0, 0, 0, 0, 0, 0, 0, 0, 0, 0, 0,
            0, 0, 0, 0, 0, 0, 0, 69, 70, 70, 70, 70, 70, 71, 0, 0, 0, 0, 0, 0, 0, 0, 0, 0, 0, 0, 0, 0,
            0, 0, 0, 0, 0, 0, 0, 78, 79, 79, 79, 79, 79, 80, 0, 0, 0, 0, 0, 0, 0, 0, 0, 0, 0, 0, 0, 0,
            0, 0, 0, 0, 0, 0, 0, 0, 0, 0, 0, 0, 0, 0, 0, 0, 0, 0, 0, 0, 0, 0, 0, 0, 0, 0, 0, 0,
            0, 0, 0, 0, 0, 0, 0, 0, 0, 0, 0, 0, 0, 0, 0, 0, 0, 0, 0, 0, 0, 0, 0, 0, 0, 0, 0, 0,
            0, 69, 70, 70, 70, 71, 0, 0, 0, 0, 0, 0, 0, 0, 0, 0, 0, 0, 0, 0, 0, 0, 0, 0, 0, 0, 0, 0,
            0, 78, 79, 79, 79, 80, 0, 0, 0, 0, 0, 0, 0, 0, 69, 71, 0, 69, 71, 0, 69, 70, 70, 70, 70, 70, 71, 0,
            0, 0, 0, 0, 0, 0, 0, 0, 0, 0, 0, 0, 0, 0, 78, 80, 0, 78, 80, 0, 78, 79, 79, 79, 79, 79, 80, 0,
            0, 0, 0, 0, 0, 0, 87, 0, 0, 0, 0, 0, 0, 0, 0, 0, 0, 0, 0, 87, 0, 0, 0, 0, 0, 0, 0, 0,
            0, 0, 0, 0, 0, 0, 79, 0, 0, 0, 0, 0, 0, 0, 0, 0, 0, 0, 0, 79, 0, 0, 0, 0, 0, 0, 0, 0,
            0, 0, 0, 0, 0, 0, 0, 0, 0, 0, 0, 0, 0, 0, 0, 0, 0, 0, 0, 0, 0, 0, 0, 0, 0, 0, 0, 0,
            0, 0, 0, 0, 0, 0, 0, 0, 0, 0, 0, 0, 0, 0, 0, 0, 0, 0, 0, 0, 0, 0, 0, 0, 0, 0, 0, 0,
            0, 0, 0, 0, 0, 0, 0, 0, 0, 0, 0, 0, 0, 0, 0, 0, 0, 0, 0, 0, 0, 0, 0, 0, 0, 0, 0, 0,
            0, 0, 0, 0, 0, 0, 0, 0, 0, 0, 0, 0, 0, 0, 0, 0, 0, 0, 0, 0, 0, 0, 0, 0, 0, 0, 0, 0,
            0, 0, 0, 0, 0, 0, 0, 0, 0, 0, 0, 0, 0, 0, 0, 0, 0, 0, 0, 0, 0, 0, 0, 0, 0, 0, 0, 0],
         "height":18,
         "id":10,
         "name":"wall",
         "opacity":1,
         "type":"tilelayer",
         "visible":true,
         "width":28,
         "x":0,
         "y":0
        }, 
        {
         "data":[0, 0, 0, 0, 0, 0, 0, 0, 0, 0, 0, 0, 0, 0, 54, 54, 54, 54, 54, 54, 54, 54, 54, 54, 54, 54, 0, 0,
            0, 0, 0, 0, 0, 0, 0, 0, 0, 0, 0, 0, 0, 0, 54, 0, 0, 0, 0, 0, 0, 0, 0, 0, 0, 54, 0, 0,
            0, 0, 0, 0, 0, 0, 0, 0, 0, 0, 0, 0, 0, 0, 54, 0, 0, 0, 0, 0, 0, 0, 0, 0, 0, 54, 0, 0,
            0, 0, 0, 0, 0, 0, 54, 54, 54, 54, 54, 54, 54, 54, 54, 0, 0, 0, 0, 0, 0, 0, 0, 0, 0, 54, 0, 0,
            0, 0, 0, 0, 0, 0, 54, 0, 0, 0, 0, 0, 0, 0, 54, 0, 0, 0, 0, 0, 0, 0, 0, 0, 0, 54, 0, 0,
            0, 0, 0, 0, 0, 0, 54, 0, 0, 0, 0, 0, 0, 0, 54, 0, 0, 0, 0, 0, 0, 0, 0, 0, 0, 54, 0, 0,
            0, 0, 0, 0, 0, 0, 54, 0, 0, 0, 0, 0, 0, 0, 54, 0, 0, 0, 0, 0, 0, 0, 0, 0, 0, 54, 0, 0,
            54, 54, 54, 54, 54, 54, 54, 0, 0, 0, 0, 0, 0, 0, 54, 0, 0, 0, 0, 0, 0, 0, 0, 0, 0, 54, 0, 0,
            54, 0, 0, 0, 0, 0, 54, 0, 0, 0, 0, 0, 0, 0, 54, 54, 0, 54, 54, 54, 54, 54, 54, 54, 54, 54, 54, 54,
            54, 0, 0, 0, 0, 0, 54, 0, 0, 0, 0, 0, 0, 0, 0, 0, 0, 0, 0, 54, 0, 0, 0, 0, 0, 0, 0, 54,
            54, 0, 0, 0, 0, 0, 54, 0, 0, 0, 0, 0, 0, 0, 0, 0, 0, 0, 0, 54, 0, 0, 0, 0, 0, 0, 0, 54,
            54, 0, 0, 0, 0, 0, 0, 0, 0, 0, 0, 0, 0, 0, 0, 0, 0, 0, 0, 0, 0, 0, 0, 0, 0, 0, 0, 54,
            54, 0, 0, 0, 0, 0, 54, 0, 0, 0, 0, 0, 0, 0, 0, 0, 0, 0, 0, 54, 0, 0, 0, 0, 0, 0, 0, 54,
            54, 0, 0, 0, 0, 0, 54, 0, 0, 0, 0, 0, 0, 0, 0, 0, 0, 0, 0, 54, 0, 0, 0, 0, 0, 0, 0, 54,
            54, 0, 0, 0, 0, 0, 54, 0, 0, 0, 0, 0, 0, 0, 0, 0, 0, 0, 0, 54, 0, 0, 0, 0, 0, 0, 0, 54,
            54, 0, 0, 0, 0, 0, 54, 0, 0, 0, 0, 0, 0, 0, 0, 0, 0, 0, 0, 54, 0, 0, 0, 0, 0, 0, 0, 54,
            54, 0, 0, 0, 0, 0, 54, 0, 0, 0, 0, 0, 0, 0, 0, 0, 0, 0, 0, 54, 54, 54, 54, 54, 54, 54, 54, 54,
            54, 54, 54, 54, 54, 54, 54, 54, 54, 54, 54, 54, 54, 54, 54, 54, 54, 54, 54, 54, 0, 0, 0, 0, 0, 0, 0, 0],
         "height":18,
         "id":11,
         "name":"roof",
         "opacity":1,
         "type":"tilelayer",
         "visible":true,
         "width":28,
         "x":0,
         "y":0
        }, 
        {
         "data":[0, 0, 0, 0, 0, 0, 0, 0, 0, 0, 0, 0, 0, 0, 0, 0, 0, 0, 0, 0, 0, 0, 0, 0, 0, 0, 0, 0,
            0, 0, 0, 0, 0, 0, 0, 0, 0, 0, 0, 0, 0, 0, 0, 0, 0, 0, 0, 0, 0, 0, 0, 0, 0, 0, 0, 0,
            0, 0, 0, 0, 0, 0, 0, 0, 0, 0, 0, 0, 0, 0, 0, 1, 1, 1, 1, 1, 1, 1, 1, 1, 1, 0, 0, 0,
            0, 0, 0, 0, 0, 0, 0, 0, 0, 0, 0, 0, 0, 0, 1, 0, 0, 0, 0, 0, 0, 0, 0, 0, 0, 1, 0, 0,
            0, 0, 0, 0, 0, 0, 0, 0, 0, 0, 0, 0, 0, 0, 1, 0, 0, 0, 0, 0, 0, 0, 0, 0, 0, 1, 0, 0,
            0, 0, 0, 0, 0, 0, 0, 1, 1, 1, 1, 1, 1, 1, 1, 0, 0, 0, 0, 0, 0, 0, 0, 0, 0, 1, 0, 0,
            0, 0, 0, 0, 0, 0, 1, 0, 0, 0, 0, 0, 0, 0, 1, 0, 0, 0, 0, 0, 0, 0, 0, 0, 0, 1, 0, 0,
            0, 0, 0, 0, 0, 0, 1, 0, 0, 0, 0, 0, 0, 0, 1, 0, 0, 0, 0, 0, 0, 0, 0, 0, 0, 1, 0, 0,
            0, 0, 0, 0, 0, 0, 1, 0, 0, 0, 0, 0, 0, 0, 1, 0, 0, 0, 0, 0, 0, 0, 0, 0, 0, 1, 0, 0,
            0, 1, 1, 1, 1, 1, 1, 0, 0, 0, 0, 0, 0, 0, 4, 3, 0, 3, 3, 3, 3, 3, 3, 3, 3, 1, 0, 0,
            1, 0, 0, 0, 0, 0, 1, 0, 0, 0, 0, 0, 0, 0, 4, 4, 0, 4, 1, 1, 1, 1, 1, 1, 1, 1, 1, 0,
            1, 0, 0, 0, 0, 0, 4, 0, 0, 0, 0, 0, 0, 0, 0, 0, 0, 0, 0, 4, 0, 0, 0, 0, 0, 0, 0, 1,
            1, 0, 0, 0, 0, 0, 4, 0, 0, 0, 0, 0, 0, 0, 0, 0, 0, 0, 0, 4, 0, 0, 0, 0, 0, 0, 0, 1,
            1, 0, 0, 0, 0, 0, 0, 0, 0, 0, 0, 0, 0, 0, 0, 0, 0, 0, 0, 0, 0, 0, 0, 0, 0, 0, 0, 1,
            1, 0, 0, 0, 0, 0, 1, 0, 0, 0, 0, 0, 0, 0, 0, 0, 0, 0, 0, 1, 0, 0, 0, 0, 0, 0, 0, 1,
            1, 0, 0, 0, 0, 0, 1, 0, 0, 0, 0, 0, 0, 0, 0, 0, 0, 0, 0, 1, 0, 0, 0, 0, 0, 0, 0, 1,
            1, 0, 0, 0, 0, 0, 1, 0, 0, 0, 0, 0, 0, 0, 0, 0, 0, 0, 0, 1, 1, 1, 1, 1, 1, 1, 1, 0,
            0, 1, 1, 1, 1, 1, 0, 1, 1, 1, 1, 1, 1, 1, 1, 1, 1, 1, 1, 0, 0, 0, 0, 0, 0, 0, 0, 0],
         "height":18,
         "id":1,
         "name":"bounds",
         "opacity":0.47,
         "type":"tilelayer",
         "visible":true,
         "width":28,
         "x":0,
         "y":0
        }, 
        {
         "id":4,
         "layers":[
                {
                 "data":[0, 0, 0, 0, 0, 0, 0, 0, 0, 0, 0, 0, 0, 0, 0, 0, 0, 0, 0, 0, 0, 0, 0, 0, 0, 0, 0, 0,
                    0, 0, 0, 0, 0, 0, 0, 0, 0, 0, 0, 0, 0, 0, 0, 0, 0, 0, 0, 0, 0, 0, 0, 0, 0, 0, 0, 0,
                    0, 0, 0, 0, 0, 0, 0, 0, 0, 0, 0, 0, 0, 0, 0, 0, 0, 0, 0, 0, 0, 0, 0, 0, 0, 0, 0, 0,
                    0, 0, 0, 0, 0, 0, 0, 0, 0, 0, 0, 0, 0, 0, 0, 0, 0, 0, 0, 0, 0, 0, 0, 0, 0, 0, 0, 0,
                    0, 0, 0, 0, 0, 0, 0, 0, 0, 0, 0, 0, 0, 0, 0, 0, 0, 0, 0, 0, 0, 0, 0, 0, 0, 0, 0, 0,
                    0, 0, 0, 0, 0, 0, 0, 0, 0, 0, 0, 0, 0, 0, 0, 0, 0, 0, 0, 0, 0, 0, 0, 0, 0, 0, 0, 0,
                    0, 0, 0, 0, 0, 0, 0, 0, 0, 0, 0, 0, 0, 0, 0, 0, 0, 0, 0, 0, 0, 0, 0, 0, 0, 0, 0, 0,
                    0, 0, 0, 0, 0, 0, 0, 0, 0, 0, 0, 0, 0, 0, 0, 0, 0, 0, 0, 0, 0, 0, 0, 0, 0, 0, 0, 0,
                    0, 0, 0, 0, 0, 0, 0, 0, 0, 0, 0, 0, 0, 0, 0, 0, 0, 0, 0, 0, 0, 0, 0, 0, 0, 0, 0, 0,
                    0, 0, 0, 0, 0, 0, 0, 0, 0, 0, 0, 0, 0, 0, 0, 0, 0, 0, 0, 0, 0, 0, 0, 0, 0, 0, 0, 0,
                    0, 0, 0, 0, 0, 0, 0, 0, 0, 0, 0, 0, 0, 0, 0, 0, 0, 0, 0, 0, 0, 0, 0, 0, 0, 0, 0, 0,
                    0, 0, 0, 0, 0, 0, 0, 0, 0, 0, 0, 0, 0, 0, 0, 0, 0, 0, 0, 0, 0, 0, 0, 0, 0, 0, 0, 0,
                    0, 0, 0, 0, 0, 0, 0, 0, 0, 0, 0, 0, 0, 0, 0, 0, 0, 0, 0, 0, 0, 0, 0, 0, 0, 0, 0, 0,
                    0, 0, 0, 0, 0, 0, 0, 0, 0, 0, 0, 0, 0, 0, 0, 0, 0, 0, 0, 0, 0, 0, 0, 0, 0, 0, 0, 0,
                    0, 0, 0, 0, 0, 0, 0, 0, 0, 0, 0, 0, 0, 0, 0, 0, 0, 0, 0, 0, 0, 0, 0, 0, 0, 0, 0, 0,
                    0, 0, 0, 0, 0, 0, 0, 0, 0, 0, 0, 0, 0, 0, 0, 0, 0, 0, 0, 0, 0, 0, 0, 0, 0, 0, 0, 0,
                    0, 0, 0, 0, 0, 0, 0, 0, 2, 2, 0, 0, 0, 0, 0, 0, 0, 0, 0, 0, 0, 0, 0, 0, 0, 0, 0, 0,
                    0, 0, 0, 0, 0, 0, 0, 0, 0, 0, 0, 0, 0, 0, 0, 0, 0, 0, 0, 0, 0, 0, 0, 0, 0, 0, 0, 0],
                 "height":18,
                 "id":3,
                 "name":"exitHome",
                 "opacity":1,
                 "properties":[
                        {
                         "name":"height",
                         "type":"int",
                         "value":1
                        }, 
                        {
                         "name":"width",
                         "type":"int",
                         "value":2
                        }, 
                        {
                         "name":"x",
                         "type":"int",
                         "value":8
                        }, 
                        {
                         "name":"y",
                         "type":"int",
                         "value":16
                        }],
                 "type":"tilelayer",
                 "visible":true,
                 "width":28,
                 "x":0,
                 "y":0
                }],
         "name":"events",
         "opacity":1,
         "type":"group",
         "visible":true,
         "x":0,
         "y":0
        }],
 "nextlayerid":12,
 "nextobjectid":1,
 "orientation":"orthogonal",
 "renderorder":"right-down",
 "tiledversion":"1.10.2",
 "tileheight":32,
 "tilesets":[
        {
         "firstgid":1,
         "source":"tileset-tsx\/bounds.tsx"
        }, 
        {
         "firstgid":5,
         "source":"tileset-tsx\/floor-wood-planks.tsx"
        }, 
        {
         "firstgid":54,
         "source":"tileset-tsx\/wall-wood-planks.tsx"
        }],
 "tilewidth":32,
 "type":"map",
 "version":"1.10",
 "width":28
}